{
  "friendslist": {
    "friends": [
      {
        "steamid": "76561197967836062",
        "relationship": "friend",
        "friend_since": 1593427140
      },
      {
        "steamid": "76561197992309281",
        "relationship": "friend",
        "friend_since": 1740471537
      },
      {
        "steamid": "76561198037411011",
        "relationship": "friend",
        "friend_since": 1719141089
      },
      {
        "steamid": "76561198051209436",
        "relationship": "friend",
        "friend_since": 1592916494
      },
      {
        "steamid": "76561198054590576",
        "relationship": "friend",
        "friend_since": 1748788178
      },
      {
        "steamid": "76561198075972569",
        "relationship": "friend",
        "friend_since": 1741107124
      },
      {
        "steamid": "76561198081892357",
        "relationship": "friend",
        "friend_since": 1724693815
      },
      {
        "steamid": "76561198093795078",
        "relationship": "friend",
        "friend_since": 1739795739
      },
      {
        "steamid": "76561198101012212",
        "relationship": "friend",
        "friend_since": 1593630715
      },
      {
        "steamid": "76561198122450099",
        "relationship": "friend",
        "friend_since": 1748419448
      },
      {
        "steamid": "76561198152354083",
        "relationship": "friend",
        "friend_since": 1694283142
      },
      {
        "steamid": "76561198152370866",
        "relationship": "friend",
        "friend_since": 1482564668
      },
      {
        "steamid": "76561198272231941",
        "relationship": "friend",
        "friend_since": 1734948878
      },
      {
        "steamid": "76561198277480980",
        "relationship": "friend",
        "friend_since": 1685702891
      },
      {
        "steamid": "76561198294610974",
        "relationship": "friend",
        "friend_since": 1739802052
      },
      {
        "steamid": "76561198296752889",
        "relationship": "friend",
        "friend_since": 1692267187
      },
      {
        "steamid": "76561198307548670",
        "relationship": "friend",
        "friend_since": 1592590490
      },
      {
        "steamid": "76561198311509225",
        "relationship": "friend",
        "friend_since": 1592590492
      },
      {
        "steamid": "76561198313395669",
        "relationship": "friend",
        "friend_since": 1692115176
      },
      {
        "steamid": "76561198335109479",
        "relationship": "friend",
        "friend_since": 1748691897
      },
      {
        "steamid": "76561198354450357",
        "relationship": "friend",
        "friend_since": 1704739895
      },
      {
        "steamid": "76561198356829964",
        "relationship": "friend",
        "friend_since": 1741359035
      },
      {
        "steamid": "76561198367035607",
        "relationship": "friend",
        "friend_since": 1704578101
      },
      {
        "steamid": "76561198422049716",
        "relationship": "friend",
        "friend_since": 1752147102
      },
      {
        "steamid": "76561198422281414",
        "relationship": "friend",
        "friend_since": 1726421599
      },
      {
        "steamid": "76561198423426013",
        "relationship": "friend",
        "friend_since": 1748690563
      },
      {
        "steamid": "76561198810642623",
        "relationship": "friend",
        "friend_since": 1732379594
      },
      {
        "steamid": "76561198853569306",
        "relationship": "friend",
        "friend_since": 1699614930
      },
      {
        "steamid": "76561198864854412",
        "relationship": "friend",
        "friend_since": 1705493124
      },
      {
        "steamid": "76561198965354123",
        "relationship": "friend",
        "friend_since": 1708188264
      },
      {
        "steamid": "76561198965664606",
        "relationship": "friend",
        "friend_since": 1704527495
      },
      {
        "steamid": "76561199005322760",
        "relationship": "friend",
        "friend_since": 1593027866
      },
      {
        "steamid": "76561199066097867",
        "relationship": "friend",
        "friend_since": 1597771634
      },
      {
        "steamid": "76561199142827050",
        "relationship": "friend",
        "friend_since": 1644871814
      },
      {
        "steamid": "76561199385575125",
        "relationship": "friend",
        "friend_since": 1739795456
      },
      {
        "steamid": "76561199446999681",
        "relationship": "friend",
        "friend_since": 1694634688
      },
      {
        "steamid": "76561199477843385",
        "relationship": "friend",
        "friend_since": 1763301014
      },
      {
        "steamid": "76561199553417088",
        "relationship": "friend",
        "friend_since": 1738155768
      },
      {
        "steamid": "76561199684641486",
        "relationship": "friend",
        "friend_since": 1725627788
      },
      {
        "steamid": "76561199689728799",
        "relationship": "friend",
        "friend_since": 1748691820
      },
      {
        "steamid": "76561199705347483",
        "relationship": "friend",
        "friend_since": 1726829445
      }
    ]
  }
}