{
  "friendslist": {
    "friends": [
      {
        "steamid": "76561197960333589",
        "relationship": "friend",
        "friend_since": 1625286784
      },
      {
        "steamid": "76561197982156744",
        "relationship": "friend",
        "friend_since": 1743617660
      },
      {
        "steamid": "76561197983086142",
        "relationship": "friend",
        "friend_since": 1378459634
      },
      {
        "steamid": "76561197989959142",
        "relationship": "friend",
        "friend_since": 1403992070
      },
      {
        "steamid": "76561197994613929",
        "relationship": "friend",
        "friend_since": 1481726882
      },
      {
        "steamid": "76561198005652607",
        "relationship": "friend",
        "friend_since": 1363820243
      },
      {
        "steamid": "76561198011004095",
        "relationship": "friend",
        "friend_since": 1361070533
      },
      {
        "steamid": "76561198013452235",
        "relationship": "friend",
        "friend_since": 1360329259
      },
      {
        "steamid": "76561198014619223",
        "relationship": "friend",
        "friend_since": 1623613650
      },
      {
        "steamid": "76561198014779141",
        "relationship": "friend",
        "friend_since": 1361065607
      },
      {
        "steamid": "76561198025401357",
        "relationship": "friend",
        "friend_since": 1395242919
      },
      {
        "steamid": "76561198038213815",
        "relationship": "friend",
        "friend_since": 1516821899
      },
      {
        "steamid": "76561198038308768",
        "relationship": "friend",
        "friend_since": 1364162181
      },
      {
        "steamid": "76561198046644868",
        "relationship": "friend",
        "friend_since": 1752886154
      },
      {
        "steamid": "76561198047086643",
        "relationship": "friend",
        "friend_since": 1362613965
      },
      {
        "steamid": "76561198047299020",
        "relationship": "friend",
        "friend_since": 1398983459
      },
      {
        "steamid": "76561198049064510",
        "relationship": "friend",
        "friend_since": 1562100302
      },
      {
        "steamid": "76561198067557169",
        "relationship": "friend",
        "friend_since": 1401305113
      },
      {
        "steamid": "76561198067928367",
        "relationship": "friend",
        "friend_since": 1405237718
      },
      {
        "steamid": "76561198069010433",
        "relationship": "friend",
        "friend_since": 1528038127
      },
      {
        "steamid": "76561198069365937",
        "relationship": "friend",
        "friend_since": 1388600767
      },
      {
        "steamid": "76561198070024706",
        "relationship": "friend",
        "friend_since": 1400497458
      },
      {
        "steamid": "76561198070264159",
        "relationship": "friend",
        "friend_since": 1360275190
      },
      {
        "steamid": "76561198072382466",
        "relationship": "friend",
        "friend_since": 1364573828
      },
      {
        "steamid": "76561198073085640",
        "relationship": "friend",
        "friend_since": 1363898178
      },
      {
        "steamid": "76561198075290288",
        "relationship": "friend",
        "friend_since": 1621381302
      },
      {
        "steamid": "76561198081097679",
        "relationship": "friend",
        "friend_since": 1360275365
      },
      {
        "steamid": "76561198081973224",
        "relationship": "friend",
        "friend_since": 1408810002
      },
      {
        "steamid": "76561198089788995",
        "relationship": "friend",
        "friend_since": 1401542738
      },
      {
        "steamid": "76561198091156087",
        "relationship": "friend",
        "friend_since": 1399928000
      },
      {
        "steamid": "76561198094447748",
        "relationship": "friend",
        "friend_since": 1625113301
      },
      {
        "steamid": "76561198116250657",
        "relationship": "friend",
        "friend_since": 1744564732
      },
      {
        "steamid": "76561198123227512",
        "relationship": "friend",
        "friend_since": 1410465222
      },
      {
        "steamid": "76561198138159191",
        "relationship": "friend",
        "friend_since": 1407101369
      },
      {
        "steamid": "76561198140658566",
        "relationship": "friend",
        "friend_since": 1657992486
      },
      {
        "steamid": "76561198141599197",
        "relationship": "friend",
        "friend_since": 1408810006
      },
      {
        "steamid": "76561198142544561",
        "relationship": "friend",
        "friend_since": 1406987996
      },
      {
        "steamid": "76561198143181164",
        "relationship": "friend",
        "friend_since": 1407185500
      },
      {
        "steamid": "76561198143563366",
        "relationship": "friend",
        "friend_since": 1404858106
      },
      {
        "steamid": "76561198144721259",
        "relationship": "friend",
        "friend_since": 1408825039
      },
      {
        "steamid": "76561198145265607",
        "relationship": "friend",
        "friend_since": 1405631879
      },
      {
        "steamid": "76561198145647647",
        "relationship": "friend",
        "friend_since": 1406304065
      },
      {
        "steamid": "76561198147632535",
        "relationship": "friend",
        "friend_since": 1406913225
      },
      {
        "steamid": "76561198148374442",
        "relationship": "friend",
        "friend_since": 1407185501
      },
      {
        "steamid": "76561198150879727",
        "relationship": "friend",
        "friend_since": 1408659502
      },
      {
        "steamid": "76561198153146838",
        "relationship": "friend",
        "friend_since": 1410974851
      },
      {
        "steamid": "76561198155236928",
        "relationship": "friend",
        "friend_since": 1408801489
      },
      {
        "steamid": "76561198183815682",
        "relationship": "friend",
        "friend_since": 1753019798
      },
      {
        "steamid": "76561198231752160",
        "relationship": "friend",
        "friend_since": 1652324021
      },
      {
        "steamid": "76561198238642834",
        "relationship": "friend",
        "friend_since": 1562100326
      },
      {
        "steamid": "76561198244509596",
        "relationship": "friend",
        "friend_since": 1655089373
      },
      {
        "steamid": "76561198257795794",
        "relationship": "friend",
        "friend_since": 1516817156
      },
      {
        "steamid": "76561198312275191",
        "relationship": "friend",
        "friend_since": 1752885863
      },
      {
        "steamid": "76561198324726987",
        "relationship": "friend",
        "friend_since": 1648918234
      },
      {
        "steamid": "76561198398452358",
        "relationship": "friend",
        "friend_since": 1649219526
      },
      {
        "steamid": "76561198425636421",
        "relationship": "friend",
        "friend_since": 1533320977
      },
      {
        "steamid": "76561198804517878",
        "relationship": "friend",
        "friend_since": 1626640720
      },
      {
        "steamid": "76561198849351355",
        "relationship": "friend",
        "friend_since": 1624566900
      },
      {
        "steamid": "76561198869097806",
        "relationship": "friend",
        "friend_since": 1745608875
      },
      {
        "steamid": "76561198963190009",
        "relationship": "friend",
        "friend_since": 1747449074
      },
      {
        "steamid": "76561199109744420",
        "relationship": "friend",
        "friend_since": 1743804073
      }
    ]
  }
}