{
  "friendslist": {
    "friends": [
      {
        "steamid": "76561197960268093",
        "relationship": "friend",
        "friend_since": 0
      },
      {
        "steamid": "76561197960282327",
        "relationship": "friend",
        "friend_since": 0
      },
      {
        "steamid": "76561197960352059",
        "relationship": "friend",
        "friend_since": 0
      },
      {
        "steamid": "76561197960382500",
        "relationship": "friend",
        "friend_since": 0
      },
      {
        "steamid": "76561197960422350",
        "relationship": "friend",
        "friend_since": 0
      },
      {
        "steamid": "76561197960430334",
        "relationship": "friend",
        "friend_since": 1240879394
      },
      {
        "steamid": "76561197960502597",
        "relationship": "friend",
        "friend_since": 0
      },
      {
        "steamid": "76561197960527855",
        "relationship": "friend",
        "friend_since": 0
      },
      {
        "steamid": "76561197960716116",
        "relationship": "friend",
        "friend_since": 0
      },
      {
        "steamid": "76561197961020300",
        "relationship": "friend",
        "friend_since": 1236846243
      },
      {
        "steamid": "76561197961301296",
        "relationship": "friend",
        "friend_since": 1234375648
      },
      {
        "steamid": "76561197961338757",
        "relationship": "friend",
        "friend_since": 0
      },
      {
        "steamid": "76561197961380056",
        "relationship": "friend",
        "friend_since": 0
      },
      {
        "steamid": "76561197961398131",
        "relationship": "friend",
        "friend_since": 0
      },
      {
        "steamid": "76561197961406545",
        "relationship": "friend",
        "friend_since": 0
      },
      {
        "steamid": "76561197961482014",
        "relationship": "friend",
        "friend_since": 0
      },
      {
        "steamid": "76561197961689399",
        "relationship": "friend",
        "friend_since": 0
      },
      {
        "steamid": "76561197961760004",
        "relationship": "friend",
        "friend_since": 0
      },
      {
        "steamid": "76561197961805789",
        "relationship": "friend",
        "friend_since": 1251550794
      },
      {
        "steamid": "76561197961885695",
        "relationship": "friend",
        "friend_since": 0
      },
      {
        "steamid": "76561197962031086",
        "relationship": "friend",
        "friend_since": 0
      },
      {
        "steamid": "76561197962473928",
        "relationship": "friend",
        "friend_since": 0
      },
      {
        "steamid": "76561197962867797",
        "relationship": "friend",
        "friend_since": 0
      },
      {
        "steamid": "76561197963122689",
        "relationship": "friend",
        "friend_since": 0
      },
      {
        "steamid": "76561197963468532",
        "relationship": "friend",
        "friend_since": 1241479874
      },
      {
        "steamid": "76561197963632370",
        "relationship": "friend",
        "friend_since": 0
      },
      {
        "steamid": "76561197964110611",
        "relationship": "friend",
        "friend_since": 1239375828
      },
      {
        "steamid": "76561197964366390",
        "relationship": "friend",
        "friend_since": 0
      },
      {
        "steamid": "76561197964392624",
        "relationship": "friend",
        "friend_since": 0
      },
      {
        "steamid": "76561197964436271",
        "relationship": "friend",
        "friend_since": 1251591447
      },
      {
        "steamid": "76561197965341301",
        "relationship": "friend",
        "friend_since": 1249851413
      },
      {
        "steamid": "76561197965556705",
        "relationship": "friend",
        "friend_since": 0
      },
      {
        "steamid": "76561197965627429",
        "relationship": "friend",
        "friend_since": 0
      },
      {
        "steamid": "76561197966031849",
        "relationship": "friend",
        "friend_since": 0
      },
      {
        "steamid": "76561197966435383",
        "relationship": "friend",
        "friend_since": 0
      },
      {
        "steamid": "76561197966703333",
        "relationship": "friend",
        "friend_since": 0
      },
      {
        "steamid": "76561197966858112",
        "relationship": "friend",
        "friend_since": 1246667444
      },
      {
        "steamid": "76561197967222282",
        "relationship": "friend",
        "friend_since": 0
      },
      {
        "steamid": "76561197967702493",
        "relationship": "friend",
        "friend_since": 1231266286
      },
      {
        "steamid": "76561197968393961",
        "relationship": "friend",
        "friend_since": 0
      },
      {
        "steamid": "76561197968485781",
        "relationship": "friend",
        "friend_since": 0
      },
      {
        "steamid": "76561197969006522",
        "relationship": "friend",
        "friend_since": 1233006931
      },
      {
        "steamid": "76561197969422193",
        "relationship": "friend",
        "friend_since": 0
      },
      {
        "steamid": "76561197969827379",
        "relationship": "friend",
        "friend_since": 0
      },
      {
        "steamid": "76561197970105534",
        "relationship": "friend",
        "friend_since": 0
      },
      {
        "steamid": "76561197970170456",
        "relationship": "friend",
        "friend_since": 0
      },
      {
        "steamid": "76561197970341720",
        "relationship": "friend",
        "friend_since": 1243712445
      },
      {
        "steamid": "76561197970350758",
        "relationship": "friend",
        "friend_since": 0
      },
      {
        "steamid": "76561197970437689",
        "relationship": "friend",
        "friend_since": 1296480632
      },
      {
        "steamid": "76561197970441292",
        "relationship": "friend",
        "friend_since": 1236350320
      },
      {
        "steamid": "76561197970461721",
        "relationship": "friend",
        "friend_since": 0
      },
      {
        "steamid": "76561197970595044",
        "relationship": "friend",
        "friend_since": 0
      },
      {
        "steamid": "76561197970959231",
        "relationship": "friend",
        "friend_since": 0
      },
      {
        "steamid": "76561197971271495",
        "relationship": "friend",
        "friend_since": 1242261697
      },
      {
        "steamid": "76561197971312141",
        "relationship": "friend",
        "friend_since": 0
      },
      {
        "steamid": "76561197971381405",
        "relationship": "friend",
        "friend_since": 1242918177
      },
      {
        "steamid": "76561197971612164",
        "relationship": "friend",
        "friend_since": 0
      },
      {
        "steamid": "76561197971969377",
        "relationship": "friend",
        "friend_since": 1241991283
      },
      {
        "steamid": "76561197972431362",
        "relationship": "friend",
        "friend_since": 0
      },
      {
        "steamid": "76561197973415445",
        "relationship": "friend",
        "friend_since": 0
      },
      {
        "steamid": "76561197974422137",
        "relationship": "friend",
        "friend_since": 1232147647
      },
      {
        "steamid": "76561197975523808",
        "relationship": "friend",
        "friend_since": 0
      },
      {
        "steamid": "76561197976115852",
        "relationship": "friend",
        "friend_since": 0
      },
      {
        "steamid": "76561197976537696",
        "relationship": "friend",
        "friend_since": 1231681537
      },
      {
        "steamid": "76561197977363386",
        "relationship": "friend",
        "friend_since": 0
      },
      {
        "steamid": "76561197977455846",
        "relationship": "friend",
        "friend_since": 1229896785
      },
      {
        "steamid": "76561197978228726",
        "relationship": "friend",
        "friend_since": 1247269311
      },
      {
        "steamid": "76561197978479119",
        "relationship": "friend",
        "friend_since": 1251834510
      },
      {
        "steamid": "76561197978836687",
        "relationship": "friend",
        "friend_since": 1237749848
      },
      {
        "steamid": "76561197981207159",
        "relationship": "friend",
        "friend_since": 1277845544
      },
      {
        "steamid": "76561197982423478",
        "relationship": "friend",
        "friend_since": 0
      },
      {
        "steamid": "76561197982640429",
        "relationship": "friend",
        "friend_since": 1235306878
      },
      {
        "steamid": "76561197983187484",
        "relationship": "friend",
        "friend_since": 1314137468
      },
      {
        "steamid": "76561197983504094",
        "relationship": "friend",
        "friend_since": 0
      },
      {
        "steamid": "76561197983658680",
        "relationship": "friend",
        "friend_since": 0
      },
      {
        "steamid": "76561197984277920",
        "relationship": "friend",
        "friend_since": 0
      },
      {
        "steamid": "76561197984315216",
        "relationship": "friend",
        "friend_since": 0
      },
      {
        "steamid": "76561197984417691",
        "relationship": "friend",
        "friend_since": 0
      },
      {
        "steamid": "76561197984802289",
        "relationship": "friend",
        "friend_since": 0
      },
      {
        "steamid": "76561197985531664",
        "relationship": "friend",
        "friend_since": 0
      },
      {
        "steamid": "76561197985835522",
        "relationship": "friend",
        "friend_since": 0
      },
      {
        "steamid": "76561197986584186",
        "relationship": "friend",
        "friend_since": 0
      },
      {
        "steamid": "76561197987292539",
        "relationship": "friend",
        "friend_since": 0
      },
      {
        "steamid": "76561197987355519",
        "relationship": "friend",
        "friend_since": 0
      },
      {
        "steamid": "76561197987517212",
        "relationship": "friend",
        "friend_since": 0
      },
      {
        "steamid": "76561197987665178",
        "relationship": "friend",
        "friend_since": 1254823593
      },
      {
        "steamid": "76561197987966064",
        "relationship": "friend",
        "friend_since": 0
      },
      {
        "steamid": "76561197988752854",
        "relationship": "friend",
        "friend_since": 1235409451
      },
      {
        "steamid": "76561197989264718",
        "relationship": "friend",
        "friend_since": 1235520765
      },
      {
        "steamid": "76561197989566679",
        "relationship": "friend",
        "friend_since": 0
      },
      {
        "steamid": "76561197990117572",
        "relationship": "friend",
        "friend_since": 1239822990
      },
      {
        "steamid": "76561197991239336",
        "relationship": "friend",
        "friend_since": 0
      },
      {
        "steamid": "76561197991587171",
        "relationship": "friend",
        "friend_since": 0
      },
      {
        "steamid": "76561197991623809",
        "relationship": "friend",
        "friend_since": 0
      },
      {
        "steamid": "76561197992063429",
        "relationship": "friend",
        "friend_since": 0
      },
      {
        "steamid": "76561197992166224",
        "relationship": "friend",
        "friend_since": 0
      },
      {
        "steamid": "76561197992300292",
        "relationship": "friend",
        "friend_since": 0
      },
      {
        "steamid": "76561197992731870",
        "relationship": "friend",
        "friend_since": 0
      },
      {
        "steamid": "76561197992780014",
        "relationship": "friend",
        "friend_since": 0
      },
      {
        "steamid": "76561197993305821",
        "relationship": "friend",
        "friend_since": 1237072172
      },
      {
        "steamid": "76561197993506922",
        "relationship": "friend",
        "friend_since": 0
      },
      {
        "steamid": "76561197993558933",
        "relationship": "friend",
        "friend_since": 1250721063
      },
      {
        "steamid": "76561197993586222",
        "relationship": "friend",
        "friend_since": 0
      },
      {
        "steamid": "76561197993638127",
        "relationship": "friend",
        "friend_since": 0
      },
      {
        "steamid": "76561197993780040",
        "relationship": "friend",
        "friend_since": 0
      },
      {
        "steamid": "76561197993865266",
        "relationship": "friend",
        "friend_since": 1231699784
      },
      {
        "steamid": "76561197994115824",
        "relationship": "friend",
        "friend_since": 0
      },
      {
        "steamid": "76561197994126441",
        "relationship": "friend",
        "friend_since": 0
      },
      {
        "steamid": "76561197994222717",
        "relationship": "friend",
        "friend_since": 0
      },
      {
        "steamid": "76561197994370053",
        "relationship": "friend",
        "friend_since": 0
      },
      {
        "steamid": "76561197994543682",
        "relationship": "friend",
        "friend_since": 1247838827
      },
      {
        "steamid": "76561197994717900",
        "relationship": "friend",
        "friend_since": 0
      },
      {
        "steamid": "76561197994733606",
        "relationship": "friend",
        "friend_since": 1228262389
      },
      {
        "steamid": "76561197995230536",
        "relationship": "friend",
        "friend_since": 0
      },
      {
        "steamid": "76561197995384106",
        "relationship": "friend",
        "friend_since": 1259456321
      },
      {
        "steamid": "76561197995457983",
        "relationship": "friend",
        "friend_since": 0
      },
      {
        "steamid": "76561197996676027",
        "relationship": "friend",
        "friend_since": 1248653770
      },
      {
        "steamid": "76561197996861852",
        "relationship": "friend",
        "friend_since": 1246509915
      },
      {
        "steamid": "76561197997530443",
        "relationship": "friend",
        "friend_since": 1229896785
      },
      {
        "steamid": "76561197997632804",
        "relationship": "friend",
        "friend_since": 0
      },
      {
        "steamid": "76561197997644442",
        "relationship": "friend",
        "friend_since": 1240093531
      },
      {
        "steamid": "76561197997780167",
        "relationship": "friend",
        "friend_since": 1239551485
      },
      {
        "steamid": "76561197998112581",
        "relationship": "friend",
        "friend_since": 0
      },
      {
        "steamid": "76561197999314593",
        "relationship": "friend",
        "friend_since": 1236462924
      },
      {
        "steamid": "76561198000565971",
        "relationship": "friend",
        "friend_since": 1248653771
      },
      {
        "steamid": "76561198001318100",
        "relationship": "friend",
        "friend_since": 1236729263
      },
      {
        "steamid": "76561198004384842",
        "relationship": "friend",
        "friend_since": 1246624260
      },
      {
        "steamid": "76561198004685925",
        "relationship": "friend",
        "friend_since": 1246984989
      },
      {
        "steamid": "76561198009518497",
        "relationship": "friend",
        "friend_since": 1241803729
      },
      {
        "steamid": "76561198011482672",
        "relationship": "friend",
        "friend_since": 1246624261
      },
      {
        "steamid": "76561198012019877",
        "relationship": "friend",
        "friend_since": 1249746411
      },
      {
        "steamid": "76561198021298088",
        "relationship": "friend",
        "friend_since": 1305120117
      }
    ]
  }
}