{
  "friendslist": {
    "friends": [
      {
        "steamid": "76561197961281111",
        "relationship": "friend",
        "friend_since": 1289648172
      },
      {
        "steamid": "76561197961643233",
        "relationship": "friend",
        "friend_since": 1283792419
      },
      {
        "steamid": "76561197964419503",
        "relationship": "friend",
        "friend_since": 1283301123
      },
      {
        "steamid": "76561197966272037",
        "relationship": "friend",
        "friend_since": 1258798648
      },
      {
        "steamid": "76561197967030929",
        "relationship": "friend",
        "friend_since": 1258806451
      },
      {
        "steamid": "76561197974227111",
        "relationship": "friend",
        "friend_since": 1281881103
      },
      {
        "steamid": "76561197974475428",
        "relationship": "friend",
        "friend_since": 1264766759
      },
      {
        "steamid": "76561197975290120",
        "relationship": "friend",
        "friend_since": 1283788252
      },
      {
        "steamid": "76561197980770684",
        "relationship": "friend",
        "friend_since": 1258723192
      },
      {
        "steamid": "76561197981635074",
        "relationship": "friend",
        "friend_since": 1283121722
      },
      {
        "steamid": "76561197981673865",
        "relationship": "friend",
        "friend_since": 1284171942
      },
      {
        "steamid": "76561197984818151",
        "relationship": "friend",
        "friend_since": 1258797804
      },
      {
        "steamid": "76561197989472237",
        "relationship": "friend",
        "friend_since": 1258966891
      },
      {
        "steamid": "76561197990063788",
        "relationship": "friend",
        "friend_since": 1285381479
      },
      {
        "steamid": "76561197990265414",
        "relationship": "friend",
        "friend_since": 1258816404
      },
      {
        "steamid": "76561197990597126",
        "relationship": "friend",
        "friend_since": 1284145408
      },
      {
        "steamid": "76561197992265620",
        "relationship": "friend",
        "friend_since": 1283795731
      },
      {
        "steamid": "76561197992992441",
        "relationship": "friend",
        "friend_since": 1264600130
      },
      {
        "steamid": "76561197993287611",
        "relationship": "friend",
        "friend_since": 1258765736
      },
      {
        "steamid": "76561197993346789",
        "relationship": "friend",
        "friend_since": 1269535975
      },
      {
        "steamid": "76561197997143265",
        "relationship": "friend",
        "friend_since": 1272391856
      },
      {
        "steamid": "76561197999007669",
        "relationship": "friend",
        "friend_since": 1283146114
      },
      {
        "steamid": "76561197999160540",
        "relationship": "friend",
        "friend_since": 1322437405
      },
      {
        "steamid": "76561197999669863",
        "relationship": "friend",
        "friend_since": 1258722571
      },
      {
        "steamid": "76561197999711253",
        "relationship": "friend",
        "friend_since": 1258725574
      },
      {
        "steamid": "76561198000259281",
        "relationship": "friend",
        "friend_since": 1281194500
      },
      {
        "steamid": "76561198001121612",
        "relationship": "friend",
        "friend_since": 1284734368
      },
      {
        "steamid": "76561198001964632",
        "relationship": "friend",
        "friend_since": 1282321274
      },
      {
        "steamid": "76561198002433737",
        "relationship": "friend",
        "friend_since": 1286336326
      },
      {
        "steamid": "76561198002459378",
        "relationship": "friend",
        "friend_since": 1260935513
      },
      {
        "steamid": "76561198003964877",
        "relationship": "friend",
        "friend_since": 1264590115
      },
      {
        "steamid": "76561198004207993",
        "relationship": "friend",
        "friend_since": 1283099783
      },
      {
        "steamid": "76561198005074008",
        "relationship": "friend",
        "friend_since": 1262067820
      },
      {
        "steamid": "76561198005233032",
        "relationship": "friend",
        "friend_since": 1259314912
      },
      {
        "steamid": "76561198010461976",
        "relationship": "friend",
        "friend_since": 1268325151
      },
      {
        "steamid": "76561198010595386",
        "relationship": "friend",
        "friend_since": 1285149789
      },
      {
        "steamid": "76561198010965439",
        "relationship": "friend",
        "friend_since": 1283528394
      },
      {
        "steamid": "76561198011374081",
        "relationship": "friend",
        "friend_since": 1264513100
      },
      {
        "steamid": "76561198011378996",
        "relationship": "friend",
        "friend_since": 1272120777
      },
      {
        "steamid": "76561198011743658",
        "relationship": "friend",
        "friend_since": 1284990628
      },
      {
        "steamid": "76561198011925231",
        "relationship": "friend",
        "friend_since": 1283082410
      },
      {
        "steamid": "76561198012215075",
        "relationship": "friend",
        "friend_since": 1284599336
      },
      {
        "steamid": "76561198013570610",
        "relationship": "friend",
        "friend_since": 1328788074
      },
      {
        "steamid": "76561198014307271",
        "relationship": "friend",
        "friend_since": 1288273348
      },
      {
        "steamid": "76561198014422959",
        "relationship": "friend",
        "friend_since": 1258725626
      },
      {
        "steamid": "76561198014540487",
        "relationship": "friend",
        "friend_since": 1260090853
      },
      {
        "steamid": "76561198014807410",
        "relationship": "friend",
        "friend_since": 1258800745
      },
      {
        "steamid": "76561198015080774",
        "relationship": "friend",
        "friend_since": 1258783579
      },
      {
        "steamid": "76561198015338357",
        "relationship": "friend",
        "friend_since": 1258863623
      },
      {
        "steamid": "76561198015369261",
        "relationship": "friend",
        "friend_since": 1262188955
      },
      {
        "steamid": "76561198015535100",
        "relationship": "friend",
        "friend_since": 1270491836
      },
      {
        "steamid": "76561198015570194",
        "relationship": "friend",
        "friend_since": 1258816545
      },
      {
        "steamid": "76561198015635023",
        "relationship": "friend",
        "friend_since": 1258723292
      },
      {
        "steamid": "76561198015641243",
        "relationship": "friend",
        "friend_since": 1258968652
      },
      {
        "steamid": "76561198015704572",
        "relationship": "friend",
        "friend_since": 1262188957
      },
      {
        "steamid": "76561198015737919",
        "relationship": "friend",
        "friend_since": 1284294426
      },
      {
        "steamid": "76561198015795500",
        "relationship": "friend",
        "friend_since": 1283088788
      },
      {
        "steamid": "76561198015925300",
        "relationship": "friend",
        "friend_since": 1283260079
      },
      {
        "steamid": "76561198016039270",
        "relationship": "friend",
        "friend_since": 1281806262
      },
      {
        "steamid": "76561198016485090",
        "relationship": "friend",
        "friend_since": 1268493688
      },
      {
        "steamid": "76561198016496168",
        "relationship": "friend",
        "friend_since": 1273924424
      },
      {
        "steamid": "76561198016514123",
        "relationship": "friend",
        "friend_since": 1283082050
      },
      {
        "steamid": "76561198016572680",
        "relationship": "friend",
        "friend_since": 1268453294
      },
      {
        "steamid": "76561198016620257",
        "relationship": "friend",
        "friend_since": 1284810506
      },
      {
        "steamid": "76561198016637127",
        "relationship": "friend",
        "friend_since": 1406037037
      },
      {
        "steamid": "76561198016641828",
        "relationship": "friend",
        "friend_since": 1269604904
      },
      {
        "steamid": "76561198016688796",
        "relationship": "friend",
        "friend_since": 1281850270
      },
      {
        "steamid": "76561198016696015",
        "relationship": "friend",
        "friend_since": 1261139253
      },
      {
        "steamid": "76561198017075238",
        "relationship": "friend",
        "friend_since": 1262707471
      },
      {
        "steamid": "76561198017310881",
        "relationship": "friend",
        "friend_since": 1262188961
      },
      {
        "steamid": "76561198017343875",
        "relationship": "friend",
        "friend_since": 1292590394
      },
      {
        "steamid": "76561198017438301",
        "relationship": "friend",
        "friend_since": 1286000765
      },
      {
        "steamid": "76561198017493409",
        "relationship": "friend",
        "friend_since": 1284731838
      },
      {
        "steamid": "76561198017494643",
        "relationship": "friend",
        "friend_since": 1283142983
      },
      {
        "steamid": "76561198017510483",
        "relationship": "friend",
        "friend_since": 1283082443
      },
      {
        "steamid": "76561198017854299",
        "relationship": "friend",
        "friend_since": 1268526358
      },
      {
        "steamid": "76561198017916458",
        "relationship": "friend",
        "friend_since": 1272945029
      },
      {
        "steamid": "76561198017978941",
        "relationship": "friend",
        "friend_since": 1282410270
      },
      {
        "steamid": "76561198018074848",
        "relationship": "friend",
        "friend_since": 1260960305
      },
      {
        "steamid": "76561198018092800",
        "relationship": "friend",
        "friend_since": 1470724179
      },
      {
        "steamid": "76561198018196963",
        "relationship": "friend",
        "friend_since": 1282123225
      },
      {
        "steamid": "76561198018267249",
        "relationship": "friend",
        "friend_since": 1282924048
      },
      {
        "steamid": "76561198018474103",
        "relationship": "friend",
        "friend_since": 1284731823
      },
      {
        "steamid": "76561198018485243",
        "relationship": "friend",
        "friend_since": 1264770607
      },
      {
        "steamid": "76561198018524230",
        "relationship": "friend",
        "friend_since": 1264860608
      },
      {
        "steamid": "76561198019134925",
        "relationship": "friend",
        "friend_since": 1283267345
      },
      {
        "steamid": "76561198019440880",
        "relationship": "friend",
        "friend_since": 1263088971
      },
      {
        "steamid": "76561198019664860",
        "relationship": "friend",
        "friend_since": 1313061246
      },
      {
        "steamid": "76561198019787912",
        "relationship": "friend",
        "friend_since": 1284731817
      },
      {
        "steamid": "76561198019829355",
        "relationship": "friend",
        "friend_since": 1268759077
      },
      {
        "steamid": "76561198019928097",
        "relationship": "friend",
        "friend_since": 1268152435
      },
      {
        "steamid": "76561198019939975",
        "relationship": "friend",
        "friend_since": 1285335931
      },
      {
        "steamid": "76561198020025881",
        "relationship": "friend",
        "friend_since": 1283794350
      },
      {
        "steamid": "76561198020069032",
        "relationship": "friend",
        "friend_since": 1287928652
      },
      {
        "steamid": "76561198020288826",
        "relationship": "friend",
        "friend_since": 1285153394
      },
      {
        "steamid": "76561198020370022",
        "relationship": "friend",
        "friend_since": 1268382434
      },
      {
        "steamid": "76561198020419565",
        "relationship": "friend",
        "friend_since": 1268836485
      },
      {
        "steamid": "76561198020582771",
        "relationship": "friend",
        "friend_since": 1283082415
      },
      {
        "steamid": "76561198021151373",
        "relationship": "friend",
        "friend_since": 1268976259
      },
      {
        "steamid": "76561198021350842",
        "relationship": "friend",
        "friend_since": 1284731823
      },
      {
        "steamid": "76561198021351702",
        "relationship": "friend",
        "friend_since": 1269954733
      },
      {
        "steamid": "76561198021404028",
        "relationship": "friend",
        "friend_since": 1268113055
      },
      {
        "steamid": "76561198021404512",
        "relationship": "friend",
        "friend_since": 1268114507
      },
      {
        "steamid": "76561198021501605",
        "relationship": "friend",
        "friend_since": 1268210628
      },
      {
        "steamid": "76561198021501979",
        "relationship": "friend",
        "friend_since": 1268141100
      },
      {
        "steamid": "76561198021505073",
        "relationship": "friend",
        "friend_since": 1268113080
      },
      {
        "steamid": "76561198021571626",
        "relationship": "friend",
        "friend_since": 1268394200
      },
      {
        "steamid": "76561198021572602",
        "relationship": "friend",
        "friend_since": 1268153503
      },
      {
        "steamid": "76561198021659468",
        "relationship": "friend",
        "friend_since": 1268116517
      },
      {
        "steamid": "76561198021661845",
        "relationship": "friend",
        "friend_since": 1269535977
      },
      {
        "steamid": "76561198021662563",
        "relationship": "friend",
        "friend_since": 1268113198
      },
      {
        "steamid": "76561198021664907",
        "relationship": "friend",
        "friend_since": 1268192783
      },
      {
        "steamid": "76561198021742474",
        "relationship": "friend",
        "friend_since": 1287370127
      },
      {
        "steamid": "76561198021762791",
        "relationship": "friend",
        "friend_since": 1272120780
      },
      {
        "steamid": "76561198021852070",
        "relationship": "friend",
        "friend_since": 1268126167
      },
      {
        "steamid": "76561198021891232",
        "relationship": "friend",
        "friend_since": 1268599549
      },
      {
        "steamid": "76561198021897993",
        "relationship": "friend",
        "friend_since": 1268307850
      },
      {
        "steamid": "76561198022200495",
        "relationship": "friend",
        "friend_since": 1280245632
      },
      {
        "steamid": "76561198022309973",
        "relationship": "friend",
        "friend_since": 1282924049
      },
      {
        "steamid": "76561198022431971",
        "relationship": "friend",
        "friend_since": 1283065820
      },
      {
        "steamid": "76561198022441807",
        "relationship": "friend",
        "friend_since": 1284902668
      },
      {
        "steamid": "76561198022457712",
        "relationship": "friend",
        "friend_since": 1283658558
      },
      {
        "steamid": "76561198022614278",
        "relationship": "friend",
        "friend_since": 1283099793
      },
      {
        "steamid": "76561198023074170",
        "relationship": "friend",
        "friend_since": 1283791244
      },
      {
        "steamid": "76561198023236446",
        "relationship": "friend",
        "friend_since": 1288264354
      },
      {
        "steamid": "76561198024029635",
        "relationship": "friend",
        "friend_since": 1284732770
      },
      {
        "steamid": "76561198024763564",
        "relationship": "friend",
        "friend_since": 1284470775
      },
      {
        "steamid": "76561198026051954",
        "relationship": "friend",
        "friend_since": 1281841361
      },
      {
        "steamid": "76561198028655751",
        "relationship": "friend",
        "friend_since": 1286089944
      },
      {
        "steamid": "76561198029241507",
        "relationship": "friend",
        "friend_since": 1283087626
      },
      {
        "steamid": "76561198029721627",
        "relationship": "friend",
        "friend_since": 1284731822
      },
      {
        "steamid": "76561198031717088",
        "relationship": "friend",
        "friend_since": 1288779056
      },
      {
        "steamid": "76561198978869400",
        "relationship": "friend",
        "friend_since": 1566386650
      }
    ]
  }
}