{
  "friendslist": {
    "friends": [
      {
        "steamid": "76561197960273775",
        "relationship": "friend",
        "friend_since": 0
      },
      {
        "steamid": "76561197960281482",
        "relationship": "friend",
        "friend_since": 1266010676
      },
      {
        "steamid": "76561197960301906",
        "relationship": "friend",
        "friend_since": 1242593819
      },
      {
        "steamid": "76561197960317684",
        "relationship": "friend",
        "friend_since": 1268157760
      },
      {
        "steamid": "76561197960380810",
        "relationship": "friend",
        "friend_since": 0
      },
      {
        "steamid": "76561197960389002",
        "relationship": "friend",
        "friend_since": 1267126521
      },
      {
        "steamid": "76561197960392580",
        "relationship": "friend",
        "friend_since": 0
      },
      {
        "steamid": "76561197960394475",
        "relationship": "friend",
        "friend_since": 1244439144
      },
      {
        "steamid": "76561197960412716",
        "relationship": "friend",
        "friend_since": 0
      },
      {
        "steamid": "76561197960413911",
        "relationship": "friend",
        "friend_since": 0
      },
      {
        "steamid": "76561197960419446",
        "relationship": "friend",
        "friend_since": 0
      },
      {
        "steamid": "76561197960419719",
        "relationship": "friend",
        "friend_since": 0
      },
      {
        "steamid": "76561197960421559",
        "relationship": "friend",
        "friend_since": 1224454430
      },
      {
        "steamid": "76561197960478885",
        "relationship": "friend",
        "friend_since": 1267528550
      },
      {
        "steamid": "76561197960519422",
        "relationship": "friend",
        "friend_since": 1344486113
      },
      {
        "steamid": "76561197960524233",
        "relationship": "friend",
        "friend_since": 1276128658
      },
      {
        "steamid": "76561197960537927",
        "relationship": "friend",
        "friend_since": 1240531579
      },
      {
        "steamid": "76561197960544744",
        "relationship": "friend",
        "friend_since": 0
      },
      {
        "steamid": "76561197960567243",
        "relationship": "friend",
        "friend_since": 0
      },
      {
        "steamid": "76561197960614650",
        "relationship": "friend",
        "friend_since": 0
      },
      {
        "steamid": "76561197960658543",
        "relationship": "friend",
        "friend_since": 0
      },
      {
        "steamid": "76561197960683630",
        "relationship": "friend",
        "friend_since": 1454708970
      },
      {
        "steamid": "76561197960782160",
        "relationship": "friend",
        "friend_since": 0
      },
      {
        "steamid": "76561197960790668",
        "relationship": "friend",
        "friend_since": 1262997262
      },
      {
        "steamid": "76561197960942935",
        "relationship": "friend",
        "friend_since": 0
      },
      {
        "steamid": "76561197960951902",
        "relationship": "friend",
        "friend_since": 0
      },
      {
        "steamid": "76561197961065394",
        "relationship": "friend",
        "friend_since": 0
      },
      {
        "steamid": "76561197961090932",
        "relationship": "friend",
        "friend_since": 1236129646
      },
      {
        "steamid": "76561197961093808",
        "relationship": "friend",
        "friend_since": 0
      },
      {
        "steamid": "76561197961108555",
        "relationship": "friend",
        "friend_since": 1272952625
      },
      {
        "steamid": "76561197961147498",
        "relationship": "friend",
        "friend_since": 1235619930
      },
      {
        "steamid": "76561197961219237",
        "relationship": "friend",
        "friend_since": 1239237046
      },
      {
        "steamid": "76561197961269735",
        "relationship": "friend",
        "friend_since": 1236528527
      },
      {
        "steamid": "76561197961281788",
        "relationship": "friend",
        "friend_since": 0
      },
      {
        "steamid": "76561197961296432",
        "relationship": "friend",
        "friend_since": 1234725417
      },
      {
        "steamid": "76561197961306772",
        "relationship": "friend",
        "friend_since": 0
      },
      {
        "steamid": "76561197961322731",
        "relationship": "friend",
        "friend_since": 1346986924
      },
      {
        "steamid": "76561197961331622",
        "relationship": "friend",
        "friend_since": 0
      },
      {
        "steamid": "76561197961373445",
        "relationship": "friend",
        "friend_since": 1595555781
      },
      {
        "steamid": "76561197961378722",
        "relationship": "friend",
        "friend_since": 1342202492
      },
      {
        "steamid": "76561197961405142",
        "relationship": "friend",
        "friend_since": 0
      },
      {
        "steamid": "76561197961410361",
        "relationship": "friend",
        "friend_since": 0
      },
      {
        "steamid": "76561197961561056",
        "relationship": "friend",
        "friend_since": 0
      },
      {
        "steamid": "76561197961561975",
        "relationship": "friend",
        "friend_since": 0
      },
      {
        "steamid": "76561197961572531",
        "relationship": "friend",
        "friend_since": 0
      },
      {
        "steamid": "76561197961611550",
        "relationship": "friend",
        "friend_since": 1346294689
      },
      {
        "steamid": "76561197961633023",
        "relationship": "friend",
        "friend_since": 0
      },
      {
        "steamid": "76561197961782479",
        "relationship": "friend",
        "friend_since": 1244410521
      },
      {
        "steamid": "76561197961867261",
        "relationship": "friend",
        "friend_since": 0
      },
      {
        "steamid": "76561197962048545",
        "relationship": "friend",
        "friend_since": 0
      },
      {
        "steamid": "76561197962217533",
        "relationship": "friend",
        "friend_since": 0
      },
      {
        "steamid": "76561197962260122",
        "relationship": "friend",
        "friend_since": 0
      },
      {
        "steamid": "76561197962429680",
        "relationship": "friend",
        "friend_since": 0
      },
      {
        "steamid": "76561197962483630",
        "relationship": "friend",
        "friend_since": 0
      },
      {
        "steamid": "76561197962663523",
        "relationship": "friend",
        "friend_since": 0
      },
      {
        "steamid": "76561197962705125",
        "relationship": "friend",
        "friend_since": 0
      },
      {
        "steamid": "76561197963119708",
        "relationship": "friend",
        "friend_since": 0
      },
      {
        "steamid": "76561197963140261",
        "relationship": "friend",
        "friend_since": 0
      },
      {
        "steamid": "76561197963145225",
        "relationship": "friend",
        "friend_since": 0
      },
      {
        "steamid": "76561197963321023",
        "relationship": "friend",
        "friend_since": 0
      },
      {
        "steamid": "76561197963370100",
        "relationship": "friend",
        "friend_since": 0
      },
      {
        "steamid": "76561197963424231",
        "relationship": "friend",
        "friend_since": 0
      },
      {
        "steamid": "76561197963524936",
        "relationship": "friend",
        "friend_since": 1266941847
      },
      {
        "steamid": "76561197963653581",
        "relationship": "friend",
        "friend_since": 0
      },
      {
        "steamid": "76561197963752994",
        "relationship": "friend",
        "friend_since": 0
      },
      {
        "steamid": "76561197964144873",
        "relationship": "friend",
        "friend_since": 0
      },
      {
        "steamid": "76561197964516935",
        "relationship": "friend",
        "friend_since": 1371420287
      },
      {
        "steamid": "76561197965007553",
        "relationship": "friend",
        "friend_since": 1236059584
      },
      {
        "steamid": "76561197965344724",
        "relationship": "friend",
        "friend_since": 1261159669
      },
      {
        "steamid": "76561197965392580",
        "relationship": "friend",
        "friend_since": 0
      },
      {
        "steamid": "76561197965704516",
        "relationship": "friend",
        "friend_since": 0
      },
      {
        "steamid": "76561197965889547",
        "relationship": "friend",
        "friend_since": 0
      },
      {
        "steamid": "76561197966008347",
        "relationship": "friend",
        "friend_since": 0
      },
      {
        "steamid": "76561197966055749",
        "relationship": "friend",
        "friend_since": 1257570503
      },
      {
        "steamid": "76561197966127567",
        "relationship": "friend",
        "friend_since": 0
      },
      {
        "steamid": "76561197966506923",
        "relationship": "friend",
        "friend_since": 1243033019
      },
      {
        "steamid": "76561197966740013",
        "relationship": "friend",
        "friend_since": 1427946007
      },
      {
        "steamid": "76561197967419377",
        "relationship": "friend",
        "friend_since": 1263453530
      },
      {
        "steamid": "76561197967454018",
        "relationship": "friend",
        "friend_since": 0
      },
      {
        "steamid": "76561197967491803",
        "relationship": "friend",
        "friend_since": 1343612949
      },
      {
        "steamid": "76561197967646798",
        "relationship": "friend",
        "friend_since": 0
      },
      {
        "steamid": "76561197967708740",
        "relationship": "friend",
        "friend_since": 0
      },
      {
        "steamid": "76561197967902972",
        "relationship": "friend",
        "friend_since": 0
      },
      {
        "steamid": "76561197968176073",
        "relationship": "friend",
        "friend_since": 1279147485
      },
      {
        "steamid": "76561197968580473",
        "relationship": "friend",
        "friend_since": 0
      },
      {
        "steamid": "76561197968598034",
        "relationship": "friend",
        "friend_since": 0
      },
      {
        "steamid": "76561197968906439",
        "relationship": "friend",
        "friend_since": 1247497938
      },
      {
        "steamid": "76561197968925708",
        "relationship": "friend",
        "friend_since": 0
      },
      {
        "steamid": "76561197969150455",
        "relationship": "friend",
        "friend_since": 1240012226
      },
      {
        "steamid": "76561197969249837",
        "relationship": "friend",
        "friend_since": 0
      },
      {
        "steamid": "76561197969308867",
        "relationship": "friend",
        "friend_since": 0
      },
      {
        "steamid": "76561197969810813",
        "relationship": "friend",
        "friend_since": 0
      },
      {
        "steamid": "76561197970186934",
        "relationship": "friend",
        "friend_since": 0
      },
      {
        "steamid": "76561197970259743",
        "relationship": "friend",
        "friend_since": 0
      },
      {
        "steamid": "76561197970481704",
        "relationship": "friend",
        "friend_since": 1240531581
      },
      {
        "steamid": "76561197970634146",
        "relationship": "friend",
        "friend_since": 1240095846
      },
      {
        "steamid": "76561197970658422",
        "relationship": "friend",
        "friend_since": 0
      },
      {
        "steamid": "76561197971090365",
        "relationship": "friend",
        "friend_since": 0
      },
      {
        "steamid": "76561197972321076",
        "relationship": "friend",
        "friend_since": 1432699831
      },
      {
        "steamid": "76561197972434818",
        "relationship": "friend",
        "friend_since": 0
      },
      {
        "steamid": "76561197973618654",
        "relationship": "friend",
        "friend_since": 0
      },
      {
        "steamid": "76561197974156389",
        "relationship": "friend",
        "friend_since": 1422812614
      },
      {
        "steamid": "76561197974896495",
        "relationship": "friend",
        "friend_since": 0
      },
      {
        "steamid": "76561197974911394",
        "relationship": "friend",
        "friend_since": 0
      },
      {
        "steamid": "76561197974951507",
        "relationship": "friend",
        "friend_since": 0
      },
      {
        "steamid": "76561197975388366",
        "relationship": "friend",
        "friend_since": 1456729512
      },
      {
        "steamid": "76561197977241935",
        "relationship": "friend",
        "friend_since": 0
      },
      {
        "steamid": "76561197977398147",
        "relationship": "friend",
        "friend_since": 0
      },
      {
        "steamid": "76561197977791082",
        "relationship": "friend",
        "friend_since": 1269197936
      },
      {
        "steamid": "76561197977905587",
        "relationship": "friend",
        "friend_since": 1456730284
      },
      {
        "steamid": "76561197978033125",
        "relationship": "friend",
        "friend_since": 1234130781
      },
      {
        "steamid": "76561197979551223",
        "relationship": "friend",
        "friend_since": 0
      },
      {
        "steamid": "76561197982596785",
        "relationship": "friend",
        "friend_since": 1433210609
      },
      {
        "steamid": "76561197982933882",
        "relationship": "friend",
        "friend_since": 1249228554
      },
      {
        "steamid": "76561197983181816",
        "relationship": "friend",
        "friend_since": 1242319245
      },
      {
        "steamid": "76561197983491300",
        "relationship": "friend",
        "friend_since": 1241312000
      },
      {
        "steamid": "76561197984030471",
        "relationship": "friend",
        "friend_since": 0
      },
      {
        "steamid": "76561197985123349",
        "relationship": "friend",
        "friend_since": 0
      },
      {
        "steamid": "76561197990181943",
        "relationship": "friend",
        "friend_since": 1258322451
      },
      {
        "steamid": "76561197992604123",
        "relationship": "friend",
        "friend_since": 0
      },
      {
        "steamid": "76561197992694988",
        "relationship": "friend",
        "friend_since": 0
      },
      {
        "steamid": "76561197993312801",
        "relationship": "friend",
        "friend_since": 1261715875
      },
      {
        "steamid": "76561197993649002",
        "relationship": "friend",
        "friend_since": 1237428497
      },
      {
        "steamid": "76561197995434815",
        "relationship": "friend",
        "friend_since": 0
      },
      {
        "steamid": "76561197995680856",
        "relationship": "friend",
        "friend_since": 1432600268
      },
      {
        "steamid": "76561197997198143",
        "relationship": "friend",
        "friend_since": 0
      },
      {
        "steamid": "76561197997515193",
        "relationship": "friend",
        "friend_since": 0
      },
      {
        "steamid": "76561197997641504",
        "relationship": "friend",
        "friend_since": 1348007105
      },
      {
        "steamid": "76561197997903868",
        "relationship": "friend",
        "friend_since": 1233980643
      },
      {
        "steamid": "76561197998429445",
        "relationship": "friend",
        "friend_since": 1237698398
      },
      {
        "steamid": "76561197999775589",
        "relationship": "friend",
        "friend_since": 0
      },
      {
        "steamid": "76561198000257455",
        "relationship": "friend",
        "friend_since": 1345233435
      },
      {
        "steamid": "76561198003957799",
        "relationship": "friend",
        "friend_since": 1234130779
      },
      {
        "steamid": "76561198024224770",
        "relationship": "friend",
        "friend_since": 1282788505
      },
      {
        "steamid": "76561198031066071",
        "relationship": "friend",
        "friend_since": 1424128598
      },
      {
        "steamid": "76561198066354952",
        "relationship": "friend",
        "friend_since": 1463354842
      },
      {
        "steamid": "76561198069679994",
        "relationship": "friend",
        "friend_since": 1587777867
      },
      {
        "steamid": "76561198085522790",
        "relationship": "friend",
        "friend_since": 1424128605
      },
      {
        "steamid": "76561198126322103",
        "relationship": "friend",
        "friend_since": 1425344415
      },
      {
        "steamid": "76561198126683822",
        "relationship": "friend",
        "friend_since": 1624759351
      },
      {
        "steamid": "76561198141300693",
        "relationship": "friend",
        "friend_since": 1603238958
      },
      {
        "steamid": "76561198154283646",
        "relationship": "friend",
        "friend_since": 1589847218
      },
      {
        "steamid": "76561198156106183",
        "relationship": "friend",
        "friend_since": 1424190762
      },
      {
        "steamid": "76561198156277652",
        "relationship": "friend",
        "friend_since": 1579225492
      },
      {
        "steamid": "76561198166336554",
        "relationship": "friend",
        "friend_since": 1432752583
      },
      {
        "steamid": "76561198178734106",
        "relationship": "friend",
        "friend_since": 1611138432
      },
      {
        "steamid": "76561198182992597",
        "relationship": "friend",
        "friend_since": 1449193680
      },
      {
        "steamid": "76561198188115594",
        "relationship": "friend",
        "friend_since": 1463354833
      },
      {
        "steamid": "76561198193852055",
        "relationship": "friend",
        "friend_since": 1535849872
      },
      {
        "steamid": "76561198202810068",
        "relationship": "friend",
        "friend_since": 1423546216
      },
      {
        "steamid": "76561198207877380",
        "relationship": "friend",
        "friend_since": 1422203885
      },
      {
        "steamid": "76561198224387096",
        "relationship": "friend",
        "friend_since": 1448634938
      },
      {
        "steamid": "76561198225849740",
        "relationship": "friend",
        "friend_since": 1433286918
      },
      {
        "steamid": "76561198251245182",
        "relationship": "friend",
        "friend_since": 1449290205
      },
      {
        "steamid": "76561198323086115",
        "relationship": "friend",
        "friend_since": 1660091942
      },
      {
        "steamid": "76561198425208936",
        "relationship": "friend",
        "friend_since": 1593653370
      }
    ]
  }
}