{
  "friendslist": {
    "friends": [
      {
        "steamid": "76561197962927693",
        "relationship": "friend",
        "friend_since": 1696265687
      },
      {
        "steamid": "76561198016253314",
        "relationship": "friend",
        "friend_since": 1612550396
      },
      {
        "steamid": "76561198025432021",
        "relationship": "friend",
        "friend_since": 1728001750
      },
      {
        "steamid": "76561198047534928",
        "relationship": "friend",
        "friend_since": 1612538067
      },
      {
        "steamid": "76561198106160890",
        "relationship": "friend",
        "friend_since": 1675018927
      },
      {
        "steamid": "76561198388278877",
        "relationship": "friend",
        "friend_since": 1594904045
      },
      {
        "steamid": "76561198395387726",
        "relationship": "friend",
        "friend_since": 1751201445
      },
      {
        "steamid": "76561198396775960",
        "relationship": "friend",
        "friend_since": 1594035562
      },
      {
        "steamid": "76561198403742441",
        "relationship": "friend",
        "friend_since": 1617180371
      },
      {
        "steamid": "76561198439289448",
        "relationship": "friend",
        "friend_since": 1577889248
      },
      {
        "steamid": "76561198852063294",
        "relationship": "friend",
        "friend_since": 1594025828
      },
      {
        "steamid": "76561198868708287",
        "relationship": "friend",
        "friend_since": 1601908636
      },
      {
        "steamid": "76561198873656274",
        "relationship": "friend",
        "friend_since": 1711092893
      },
      {
        "steamid": "76561198929996504",
        "relationship": "friend",
        "friend_since": 1748900378
      },
      {
        "steamid": "76561198968843647",
        "relationship": "friend",
        "friend_since": 1586969187
      },
      {
        "steamid": "76561198982589190",
        "relationship": "friend",
        "friend_since": 1630186545
      },
      {
        "steamid": "76561199002374698",
        "relationship": "friend",
        "friend_since": 1631451436
      },
      {
        "steamid": "76561199009814772",
        "relationship": "friend",
        "friend_since": 1630175487
      },
      {
        "steamid": "76561199029997689",
        "relationship": "friend",
        "friend_since": 1696444663
      },
      {
        "steamid": "76561199036505015",
        "relationship": "friend",
        "friend_since": 1607693511
      },
      {
        "steamid": "76561199040064648",
        "relationship": "friend",
        "friend_since": 1595086617
      },
      {
        "steamid": "76561199064628442",
        "relationship": "friend",
        "friend_since": 1645983730
      },
      {
        "steamid": "76561199066085143",
        "relationship": "friend",
        "friend_since": 1599069420
      },
      {
        "steamid": "76561199113447350",
        "relationship": "friend",
        "friend_since": 1662223045
      },
      {
        "steamid": "76561199286834764",
        "relationship": "friend",
        "friend_since": 1740004509
      },
      {
        "steamid": "76561199439530803",
        "relationship": "friend",
        "friend_since": 1727795046
      },
      {
        "steamid": "76561199572134337",
        "relationship": "friend",
        "friend_since": 1750969610
      },
      {
        "steamid": "76561199597358156",
        "relationship": "friend",
        "friend_since": 1749083566
      },
      {
        "steamid": "76561199606697820",
        "relationship": "friend",
        "friend_since": 1727795026
      },
      {
        "steamid": "76561199630081896",
        "relationship": "friend",
        "friend_since": 1707125662
      },
      {
        "steamid": "76561199818088223",
        "relationship": "friend",
        "friend_since": 1737240144
      },
      {
        "steamid": "76561199818660044",
        "relationship": "friend",
        "friend_since": 1737240239
      },
      {
        "steamid": "76561199823825610",
        "relationship": "friend",
        "friend_since": 1739997387
      },
      {
        "steamid": "76561199847405814",
        "relationship": "friend",
        "friend_since": 1747165520
      },
      {
        "steamid": "76561199869702841",
        "relationship": "friend",
        "friend_since": 1761245075
      }
    ]
  }
}